event_emitter_asyncio/EventEmitter.py
event_emitter_asyncio/EventEmitter_test.py
event_emitter_asyncio/__init__.py
event_emitter_asyncio-1.0.4.dist-info/LICENSE
event_emitter_asyncio-1.0.4.dist-info/METADATA
event_emitter_asyncio-1.0.4.dist-info/WHEEL
event_emitter_asyncio-1.0.4.dist-info/top_level.txt
event_emitter_asyncio-1.0.4.dist-info/RECORD
