Metadata-Version: 2.1
Name: event_emitter_asyncio
Version: 1.0.4
Summary: Super simple event emitter in Python 3, built with asyncio. No decorators required.
Author-email: Joel Tok <jttctc@gmail.com>
Project-URL: Homepage, https://github.com/joeltok/event-emitter-asyncio
Project-URL: Bug Tracker, https://github.com/joeltok/event-emitter-asyncio/issues
Classifier: Programming Language :: Python :: 3
Classifier: License :: OSI Approved :: MIT License
Classifier: Operating System :: OS Independent
Requires-Python: >=3.7
License-File: LICENSE
